[{"tipo":"renda variável","rentabilidade":12.0,"descricao":"Teste","risco":5.0},{"tipo":"renda variável","rentabilidade":12.0,"descricao":"Teste","risco":5.0},{"tipo":"renda variável","rentabilidade":12.0,"descricao":"Teste","risco":5.0},{"tipo":"renda variável","rentabilidade":12.0,"descricao":"Teste","risco":5.0},{"tipo":"renda variável","rentabilidade":12.0,"descricao":"Teste","risco":5.0},{"taxa":12.0,"tipo":"renda fixa","rentabilidade":12.0,"prazoMinimo":12.0,"prazoMaximo":12.0,"descricao":"TESTE"},{"tipo":"renda variável","rentabilidade":12.0,"descricao":"teste36","risco":12.0},{"tipo":"renda variável","rentabilidade":12.0,"descricao":"a","risco":112.0},{"tipo":"renda variável","rentabilidade":12.0,"descricao":"a","risco":112.0},{"tipo":"renda variável","rentabilidade":12.0,"descricao":"b","risco":112.0},{"tipo":"renda variável","rentabilidade":5.0,"descricao":"a","risco":5.0},{"taxa":1.0,"tipo":"renda fixa","rentabilidade":2.0,"prazoMinimo":2,"prazoMaximo":24,"descricao":"teste"}]