[{"nome":"Administrador","cpf":"000.000.000-00","dataNascimento":"01/01/1999","telefone":"(00) 00000-0000","email":"adm@email.com","login":"adm","senha":1234},{"nome":"ABBBBBBB","cpf":"CPF inválido","dataNascimento":"","telefone":"","email":"Email inválido","login":"BBBB","senha":123},{"nome":"TESTE","cpf":"CPF inválido","dataNascimento":"","telefone":"","email":"Email inválido","login":"","senha":123},{"nome":"aa","cpf":"CPF inválido","dataNascimento":"","telefone":"","email":"Email inválido","login":"a","senha":123,"tipoUsuario":"caixa"},{"nome":"ainda bem","cpf":"CPF inválido","dataNascimento":"","telefone":"","email":"Email inválido","login":"","senha":123,"tipoUsuario":"gerente"}]